{
  "id": 2,
  "type": "job",
  "url": "/api/v2/jobs/2/",
  "related": {
      "created_by": "/api/v2/users/1/",
      "labels": "/api/v2/jobs/2/labels/",
      "inventory": "/api/v2/inventories/1/",
      "project": "/api/v2/projects/6/",
      "credentials": "/api/v2/jobs/2/credentials/",
      "unified_job_template": "/api/v2/job_templates/7/",
      "stdout": "/api/v2/jobs/2/stdout/",
      "job_events": "/api/v2/jobs/2/job_events/",
      "job_host_summaries": "/api/v2/jobs/2/job_host_summaries/",
      "activity_stream": "/api/v2/jobs/2/activity_stream/",
      "notifications": "/api/v2/jobs/2/notifications/",
      "create_schedule": "/api/v2/jobs/2/create_schedule/",
      "job_template": "/api/v2/job_templates/7/",
      "cancel": "/api/v2/jobs/2/cancel/",
      "project_update": "/api/v2/project_updates/4/",
      "relaunch": "/api/v2/jobs/2/relaunch/"
  },
  "summary_fields": {
      "inventory": {
          "id": 1,
          "name": "Demo Inventory",
          "description": "",
          "has_active_failures": false,
          "total_hosts": 1,
          "hosts_with_active_failures": 0,
          "total_groups": 0,
          "groups_with_active_failures": 0,
          "has_inventory_sources": false,
          "total_inventory_sources": 0,
          "inventory_sources_with_failures": 0,
          "organization_id": 1,
          "kind": ""
      },
      "project": {
          "id": 6,
          "name": "Demo Project",
          "description": "",
          "status": "successful",
          "scm_type": "git"
      },
      "project_update": {
          "id": 4,
          "name": "Demo Project",
          "description": "",
          "status": "successful",
          "failed": false
      },
      "job_template": {
          "id": 7,
          "name": "Demo Job Template",
          "description": ""
      },
      "unified_job_template": {
          "id": 7,
          "name": "Demo Job Template",
          "description": "",
          "unified_job_type": "job"
      },
      "instance_group": {
          "id": 1,
          "name": "tower"
      },
      "created_by": {
          "id": 1,
          "username": "admin",
          "first_name": "",
          "last_name": ""
      },
      "user_capabilities": {
          "delete": true,
          "start": true
      },
      "labels": {
          "count": 0,
          "results": []
      },
      "credentials": [
          {
              "id": 1,
              "name": "Demo Credential",
              "description": "",
              "kind": "ssh",
              "cloud": false
          }
      ]
  },
  "created": "2019-08-08T19:24:05.344276Z",
  "modified": "2019-08-08T19:24:18.162949Z",
  "name": "Demo Job Template",
  "description": "",
  "job_type": "run",
  "inventory": 1,
  "project": 6,
  "playbook": "chatty_tasks.yml",
  "forks": 0,
  "limit": "",
  "verbosity": 0,
  "extra_vars": "{\"num_messages\": 94}",
  "job_tags": "",
  "force_handlers": false,
  "skip_tags": "",
  "start_at_task": "",
  "timeout": 0,
  "use_fact_cache": false,
  "unified_job_template": 7,
  "launch_type": "manual",
  "status": "successful",
  "failed": false,
  "started": "2019-08-08T19:24:18.329589Z",
  "finished": "2019-08-08T19:24:50.119995Z",
  "elapsed": 31.79,
  "job_args": "[\"bwrap\", \"--unshare-pid\", \"--dev-bind\", \"/\", \"/\", \"--proc\", \"/proc\", \"--bind\", \"/tmp/ansible_runner_pi_pzufy15c/ansible_runner_pi_r_aeukpy/tmpvsg8ly2y\", \"/etc/ssh\", \"--bind\", \"/tmp/ansible_runner_pi_pzufy15c/ansible_runner_pi_r_aeukpy/tmpq_grmdym\", \"/projects\", \"--bind\", \"/tmp/ansible_runner_pi_pzufy15c/ansible_runner_pi_r_aeukpy/tmpfq8ea2z6\", \"/tmp\", \"--bind\", \"/tmp/ansible_runner_pi_pzufy15c/ansible_runner_pi_r_aeukpy/tmpq6v4y_tt\", \"/var/lib/awx\", \"--bind\", \"/tmp/ansible_runner_pi_pzufy15c/ansible_runner_pi_r_aeukpy/tmpupj_jhhb\", \"/var/log\", \"--ro-bind\", \"/venv/ansible\", \"/venv/ansible\", \"--ro-bind\", \"/venv/awx\", \"/venv/awx\", \"--bind\", \"/projects/_6__demo_project\", \"/projects/_6__demo_project\", \"--bind\", \"/tmp/awx_2_a4b1afiw\", \"/tmp/awx_2_a4b1afiw\", \"--chdir\", \"/projects/_6__demo_project\", \"ansible-playbook\", \"-u\", \"admin\", \"-i\", \"/tmp/awx_2_a4b1afiw/tmppb57i4_e\", \"-e\", \"@/tmp/awx_2_a4b1afiw/env/extravars\", \"chatty_tasks.yml\"]",
  "job_cwd": "/projects/_6__demo_project",
  "job_env": {
      "HOSTNAME": "awx",
      "MAKEFLAGS": "w",
      "OS": "Operating System: Docker for Mac",
      "LC_ALL": "en_US.UTF-8",
      "SDB_HOST": "0.0.0.0",
      "MAKELEVEL": "2",
      "VIRTUAL_ENV": "/venv/ansible",
      "MFLAGS": "-w",
      "PATH": "/venv/ansible/bin:/venv/awx/bin:/venv/awx/bin:/usr/local/n/versions/node/10.15.0/bin:/usr/local/sbin:/usr/local/bin:/usr/sbin:/usr/bin:/sbin:/bin",
      "SUPERVISOR_GROUP_NAME": "tower-processes",
      "PWD": "/awx_devel",
      "LANG": "\"en-us\"",
      "PS1": "(awx) ",
      "SUPERVISOR_ENABLED": "1",
      "SHLVL": "2",
      "HOME": "/var/lib/awx",
      "LANGUAGE": "en_US:en",
      "AWX_GROUP_QUEUES": "tower",
      "SUPERVISOR_SERVER_URL": "unix:///tmp/supervisor.sock",
      "SUPERVISOR_PROCESS_NAME": "awx-dispatcher",
      "CURRENT_UID": "501",
      "_": "/venv/awx/bin/python3",
      "DJANGO_SETTINGS_MODULE": "awx.settings.development",
      "DJANGO_LIVE_TEST_SERVER_ADDRESS": "localhost:9013-9199",
      "SDB_NOTIFY_HOST": "docker.for.mac.host.internal",
      "TZ": "UTC",
      "ANSIBLE_FORCE_COLOR": "True",
      "ANSIBLE_HOST_KEY_CHECKING": "False",
      "ANSIBLE_INVENTORY_UNPARSED_FAILED": "True",
      "ANSIBLE_PARAMIKO_RECORD_HOST_KEYS": "False",
      "ANSIBLE_VENV_PATH": "/venv/ansible",
      "PROOT_TMP_DIR": "/tmp",
      "AWX_PRIVATE_DATA_DIR": "/tmp/awx_2_a4b1afiw",
      "ANSIBLE_COLLECTIONS_PATHS": "/tmp/collections",
      "PYTHONPATH": "/venv/ansible/lib/python2.7/site-packages:/awx_devel/awx/lib:",
      "JOB_ID": "2",
      "INVENTORY_ID": "1",
      "PROJECT_REVISION": "23f070aad8e2da131d97ea98b42b553ccf0b0b82",
      "ANSIBLE_RETRY_FILES_ENABLED": "False",
      "MAX_EVENT_RES": "700000",
      "ANSIBLE_CALLBACK_PLUGINS": "/awx_devel/awx/plugins/callback",
      "AWX_HOST": "https://towerhost",
      "ANSIBLE_SSH_CONTROL_PATH_DIR": "/tmp/awx_2_a4b1afiw/cp",
      "ANSIBLE_STDOUT_CALLBACK": "awx_display",
      "AWX_ISOLATED_DATA_DIR": "/tmp/awx_2_a4b1afiw/artifacts/2"
  },
  "job_explanation": "",
  "execution_node": "awx",
  "controller_node": "",
  "result_traceback": "",
  "event_processing_finished": true,
  "job_template": 7,
  "passwords_needed_to_start": [],
  "allow_simultaneous": false,
  "artifacts": {},
  "scm_revision": "23f070aad8e2da131d97ea98b42b553ccf0b0b82",
  "instance_group": 1,
  "diff_mode": false,
  "job_slice_number": 0,
  "job_slice_count": 1,
  "host_status_counts": {
      "ok": 1
  },
  "playbook_counts": {
      "play_count": 1,
      "task_count": 1
  },
  "custom_virtualenv": "/venv/ansible"
}
